nonebot_plugin_sky/__init__.py
nonebot_plugin_sky/handler.py
nonebot_plugin_sky/config/__init__.py
nonebot_plugin_sky/config/command.py
nonebot_plugin_sky/config/helper_at_all.py
nonebot_plugin_sky/config/loader.py
nonebot_plugin_sky/config/msg_forward.py
nonebot_plugin_sky/resources/menu.png
nonebot_plugin_sky/resources/images/eating.jpg
nonebot_plugin_sky/resources/images/face_braid.gif
nonebot_plugin_sky/resources/images/face_bun.gif
nonebot_plugin_sky/resources/images/face_cat.gif
nonebot_plugin_sky/resources/images/face_fox.gif
nonebot_plugin_sky/resources/images/face_white_cat.gif
nonebot_plugin_sky/resources/images/go.jpg
nonebot_plugin_sky/sky/__init__.py
nonebot_plugin_sky/sky/core.py
nonebot_plugin_sky/sky/tools.py
nonebot_plugin_sky/spider/__init__.py
nonebot_plugin_sky/spider/core.py
nonebot_plugin_sky/spider/exception.py
nonebot_plugin_sky/spider/model.py
nonebot_plugin_sky/tools/__init__.py
nonebot_plugin_sky/tools/data_pack.py
nonebot_plugin_sky/tools/restart.py
nonebot_plugin_sky/tools/scheduler.py
nonebot_plugin_sky/tools/update.py
nonebot_plugin_sky/utils/__init__.py
nonebot_plugin_sky/utils/bot_loader.py
nonebot_plugin_sky/utils/chain_reply.py
nonebot_plugin_sky/utils/date_util.py
nonebot_plugin_sky/utils/json_cards.py
nonebot_plugin_sky/utils/notice_board.py
nonebot_plugin_sky-2.5.4.dist-info/licenses/LICENSE
sky_cli/__init__.py
sky_cli/cli.py
nonebot_plugin_sky-2.5.4.dist-info/METADATA
nonebot_plugin_sky-2.5.4.dist-info/WHEEL
nonebot_plugin_sky-2.5.4.dist-info/entry_points.txt
nonebot_plugin_sky-2.5.4.dist-info/top_level.txt
nonebot_plugin_sky-2.5.4.dist-info/RECORD
