Metadata-Version: 2.4
Name: nonebot-plugin-sky
Version: 2.5.4
Summary: 基于Nonebot2的sky光遇攻略插件
Author-email: Kaguya233qwq <marisa_qwq@qq.com>
Project-URL: Homepage, https://github.com/Kaguya233qwq/nonebot_plugin_sky
Project-URL: Repository, https://github.com/Kaguya233qwq/nonebot_plugin_sky
Project-URL: Issues, https://github.com/Kaguya233qwq/nonebot_plugin_sky/issues
Keywords: nonebot2,nonebot,sky光遇,光遇
Classifier: Programming Language :: Python :: 3
Classifier: Natural Language :: Chinese (Simplified)
Requires-Python: >=3.10
License-File: LICENSE
Requires-Dist: aiofiles>=24.1.0
Requires-Dist: bs4>=0.0.2
Requires-Dist: click
Requires-Dist: httpx>=0.28.1
Requires-Dist: lxml>=6.0.0
Requires-Dist: nb-cli>=1.4.2
Requires-Dist: nonebot-adapter-onebot>=2.4.6
Requires-Dist: nonebot-plugin-apscheduler>=0.5.0
Requires-Dist: nonebot2>=2.4.2
Requires-Dist: packaging>=25.0
Requires-Dist: setuptools>=80.9.0
Dynamic: license-file
